django_tmapi-1.1.0.dist-info/DESCRIPTION.rst
django_tmapi-1.1.0.dist-info/METADATA
django_tmapi-1.1.0.dist-info/RECORD
django_tmapi-1.1.0.dist-info/WHEEL
django_tmapi-1.1.0.dist-info/metadata.json
django_tmapi-1.1.0.dist-info/pbr.json
django_tmapi-1.1.0.dist-info/top_level.txt
tmapi/__init__.py
tmapi/admin.py
tmapi/constants.py
tmapi/exceptions.py
tmapi/indices/__init__.py
tmapi/indices/index.py
tmapi/indices/literal_index.py
tmapi/indices/scoped_index.py
tmapi/indices/type_instance_index.py
tmapi/migrations/0001_initial.py
tmapi/migrations/__init__.py
tmapi/models/__init__.py
tmapi/models/association.py
tmapi/models/construct.py
tmapi/models/construct_fields.py
tmapi/models/copy_utils.py
tmapi/models/datatype_aware.py
tmapi/models/identifier.py
tmapi/models/item_identifier.py
tmapi/models/locator.py
tmapi/models/merge_utils.py
tmapi/models/name.py
tmapi/models/occurrence.py
tmapi/models/reifiable.py
tmapi/models/role.py
tmapi/models/scoped.py
tmapi/models/signature.py
tmapi/models/subject_identifier.py
tmapi/models/subject_locator.py
tmapi/models/tmapi_feature.py
tmapi/models/topic.py
tmapi/models/topic_map.py
tmapi/models/topic_map_system.py
tmapi/models/topic_map_system_factory.py
tmapi/models/typed.py
tmapi/models/variant.py
tmapi/tests/__init__.py
tmapi/tests/indices/__init__.py
tmapi/tests/indices/test_literal_index.py
tmapi/tests/indices/test_scoped_index.py
tmapi/tests/indices/test_type_instance_index.py
tmapi/tests/models/__init__.py
tmapi/tests/models/datatype_aware_abstract_tests.py
tmapi/tests/models/test_association.py
tmapi/tests/models/test_construct.py
tmapi/tests/models/test_feature_strings.py
tmapi/tests/models/test_item_identifier_constraint.py
tmapi/tests/models/test_locator.py
tmapi/tests/models/test_name.py
tmapi/tests/models/test_occurrence.py
tmapi/tests/models/test_reifiable.py
tmapi/tests/models/test_rfc3986.py
tmapi/tests/models/test_role.py
tmapi/tests/models/test_same_topic_map.py
tmapi/tests/models/test_scoped.py
tmapi/tests/models/test_topic.py
tmapi/tests/models/test_topic_map.py
tmapi/tests/models/test_topic_map_merge.py
tmapi/tests/models/test_topic_map_system.py
tmapi/tests/models/test_topic_merge.py
