Metadata-Version: 2.0
Name: django-tmapi
Version: 1.1.0
Summary: Django app providing an implementation of the Topic Maps API 2.0
Home-page: https://github.com/ajenhl/django-tmapi
Author: Jamie Norrish
Author-email: jamie@artefact.org.nz
License: Apache License, Version 2.0
Platform: UNKNOWN
Classifier: Framework :: Django
Classifier: Intended Audience :: Developers
Classifier: License :: OSI Approved :: Apache Software License
Classifier: Programming Language :: Python
Classifier: Programming Language :: Python :: 3 :: Only
